[ {
  "id" : 1,
  "nome" : "Areia",
  "descricao" : "Areia A",
  "categoriaId" : 7,
  "quantidade" : 7,
  "preco" : 99.99
}, {
  "id" : 2,
  "nome" : "Tinta Azul",
  "descricao" : "Tinta Azul",
  "categoriaId" : 1,
  "quantidade" : 10,
  "preco" : 299.99
}, {
  "id" : 3,
  "nome" : "Tinta Black",
  "descricao" : "Tinta Black",
  "categoriaId" : 1,
  "quantidade" : 9,
  "preco" : 299.99
}, {
  "id" : 4,
  "nome" : "Tinta Branca",
  "descricao" : "Tinta blanca",
  "categoriaId" : 1,
  "quantidade" : 10,
  "preco" : 249.9
}, {
  "id" : 5,
  "nome" : "Tinta",
  "descricao" : "Tinta blanca",
  "categoriaId" : 1,
  "quantidade" : 16,
  "preco" : 249.9
}, {
  "id" : 6,
  "nome" : "Bloco",
  "descricao" : "Broco P",
  "categoriaId" : 2,
  "quantidade" : 0,
  "preco" : 4.90
} ]